example/components/__init__.py
example/components/database_schema.py
example/components/http_sender.py
example/components/mysql_impl.py
example/components/persistence.py
example/components/persistence_layer.py
example/example_web/__init__.py
example/example_web/crawler.py
example/example_web/data_handler.py
example/example_web/easy_crawler.py
example/example_web/http_parser.py
example/tw_stock/__init__.py
example/tw_stock/crawler.py
example/tw_stock/data_handler.py
example/tw_stock/easy_crawlers.py
example/tw_stock/http_parser.py
smoothcrawler/__init__.py
smoothcrawler/__pkg_info__.py
smoothcrawler/crawler.py
smoothcrawler/factory.py
smoothcrawler/urls.py
smoothcrawler/components/__init__.py
smoothcrawler/components/data.py
smoothcrawler/components/httpio.py
smoothcrawler/components/persistence.py
test/components/__init__.py
test/components/data_handler.py
test/components/httpio.py
SmoothCrawler-0.2.0.dist-info/LICENSE
SmoothCrawler-0.2.0.dist-info/METADATA
SmoothCrawler-0.2.0.dist-info/WHEEL
SmoothCrawler-0.2.0.dist-info/top_level.txt
SmoothCrawler-0.2.0.dist-info/RECORD
