Metadata-Version: 2.1
Name: SmoothCrawler
Version: 0.2.0
Summary: Build crawler humanly as different roles which be combined with different components.
Home-page: https://smoothcrawler.readthedocs.io
Author: Liu, Bryant
Author-email: chi10211201@cycu.org.tw
License: Apache License 2.0
Project-URL: Documentation, https://smoothcrawler.readthedocs.io
Project-URL: Source, https://github.com/Chisanan232/smoothcrawler
Classifier: Development Status :: 3 - Alpha
Classifier: Intended Audience :: Developers
Classifier: Topic :: Software Development :: Libraries :: Python Modules
Classifier: License :: OSI Approved :: Apache Software License
Classifier: Operating System :: OS Independent
Classifier: Programming Language :: Python :: 3
Classifier: Programming Language :: Python :: 3.6
Classifier: Programming Language :: Python :: 3.7
Classifier: Programming Language :: Python :: 3.8
Classifier: Programming Language :: Python :: 3.9
Classifier: Programming Language :: Python :: 3.10
Requires-Python: >=3.6
License-File: LICENSE
Requires-Dist: multipledispatch (>=0.6.0)
Requires-Dist: multirunnable (>=0.17.0)
